portalai/__init__.py
portalai/core.py
portalai-0.1.dist-info/LICENSE
portalai-0.1.dist-info/METADATA
portalai-0.1.dist-info/WHEEL
portalai-0.1.dist-info/entry_points.txt
portalai-0.1.dist-info/top_level.txt
portalai-0.1.dist-info/RECORD
