Metadata-Version: 2.1
Name: portalai
Version: 0.1
Summary: Convert code from one language to another using AI.
Home-page: https://github.com/WolfTheDev/portal
Author: WolfTheDev
Author-email: wolfthedev@gmail.com
Classifier: Development Status :: 3 - Alpha
Classifier: Intended Audience :: Developers
Classifier: License :: OSI Approved :: MIT License
Classifier: Programming Language :: Python :: 3
Classifier: Programming Language :: Python :: 3.6
Classifier: Programming Language :: Python :: 3.7
Classifier: Programming Language :: Python :: 3.8
Classifier: Programming Language :: Python :: 3.9
License-File: LICENSE
Requires-Dist: ollama ==0.1.9
